PyStanfordDependencies-0.3.1.dist-info/METADATA
PyStanfordDependencies-0.3.1.dist-info/DESCRIPTION.rst
PyStanfordDependencies-0.3.1.dist-info/RECORD
PyStanfordDependencies-0.3.1.dist-info/WHEEL
PyStanfordDependencies-0.3.1.dist-info/metadata.json
PyStanfordDependencies-0.3.1.dist-info/top_level.txt
StanfordDependencies/CoNLL.py
StanfordDependencies/__init__.py
StanfordDependencies/JPypeBackend.py
StanfordDependencies/SubprocessBackend.py
StanfordDependencies/StanfordDependencies.py
