Metadata-Version: 2.0
Name: PyStanfordDependencies
Version: 0.3.1
Summary: Python interface for converting Penn Treebank trees to Universal Dependencies and Stanford Dependencies
Home-page: http://github.com/dmcc/PyStanfordDependencies
Author: David McClosky
Author-email: notsoweird+pystanforddependencies@gmail.com
License: Apache 2.0
Keywords: parsing,syntax,linguistics,language,artificial intelligence,machine learning,NLP,natural language,natural language processing,Stanford CoreNLP,Stanford Dependencies,Universal Dependencies
Platform: POSIX
Classifier: Development Status :: 4 - Beta
Classifier: Intended Audience :: Science/Research
Classifier: License :: OSI Approved :: Apache Software License
Classifier: Natural Language :: English
Classifier: Operating System :: POSIX
Classifier: Topic :: Scientific/Engineering :: Artificial Intelligence
Provides-Extra: visualization
Requires-Dist: asciitree; extra == 'visualization'
Requires-Dist: graphviz; extra == 'visualization'
Provides-Extra: JPype
Requires-Dist: JPype1; extra == 'JPype'
